[
    {
        "workout_plan_id": 1,
        "physique_goals": "Lose Fat / Cut",
        "name": "Cardio Burn Circuit",
        "description": "A high-intensity, fat-burning circuit workout combining cardio and bodyweight movements.",
        "goal": "Weight-Loss",
        "difficulty_level": "Intermediate",
        "duration": 45,
        "exercises": [
            "Jumping Jacks",
            "Burpees",
            "Mountain Climbers",
            "Bodyweight Squats"
        ],
        "target_muscle_groups": [
            "Full Body"
        ],
        "frequency": "daily",
        "reps": [
            20,
            15,
            20,
            25
        ],
        "sets": [
            3,
            3,
            3,
            3
        ],
        "exercise_details": [
            {
                "exercise_name": "Jumping Jacks",
                "reps": 20,
                "sets": 3
            },
            {
                "exercise_name": "Burpees",
                "reps": 15,
                "sets": 3
            },
            {
                "exercise_name": "Mountain Climbers",
                "reps": 20,
                "sets": 3
            },
            {
                "exercise_name": "Bodyweight Squats",
                "reps": 25,
                "sets": 3
            }
        ]
    },
    {
        "workout_plan_id": 2,
        "physique_goals": "Gain Muscle / Bulk",
        "name": "Strength Training Plus",
        "description": "A hypertrophy-focused strength program to build muscle mass.",
        "goal": "Strength",
        "difficulty_level": "Advanced",
        "duration": 60,
        "exercises": [
            "Barbell Bench Press",
            "Barbell Deadlift",
            "Barbell Back Squat",
            "Seated Dumbbell Shoulder Press"
        ],
        "target_muscle_groups": [
            "Upper Body",
            "Legs"
        ],
        "frequency": "weekly",
        "reps": [
            10,
            8,
            12,
            10
        ],
        "sets": [
            4,
            5,
            4,
            4
        ],
        "exercise_details": [
            {
                "exercise_name": "Barbell Bench Press",
                "reps": 10,
                "sets": 4
            },
            {
                "exercise_name": "Barbell Deadlift",
                "reps": 8,
                "sets": 5
            },
            {
                "exercise_name": "Barbell Back Squat",
                "reps": 12,
                "sets": 4
            },
            {
                "exercise_name": "Seated Dumbbell Shoulder Press",
                "reps": 10,
                "sets": 4
            }
        ]
    }
]